LICENSE
README.md
setup.py
DesignForPy/DesignForPy.py
DesignForPy/__init__.py
DesignForPy.egg-info/PKG-INFO
DesignForPy.egg-info/SOURCES.txt
DesignForPy.egg-info/dependency_links.txt
DesignForPy.egg-info/requires.txt
DesignForPy.egg-info/top_level.txt