Metadata-Version: 2.1
Name: DesignForPy
Version: 1.0
Summary: An amazing Design for Python
Author: Gustavo Martinez
Author-email: gamezinhoo@outlook.com
License: MIT License
Keywords: design
License-File: LICENSE
